{
  "title": "इमोजी के साथ रैंडम टेक्स्ट जेनरेटर",
  "description": "इमोजी से भरा मज़ेदार, यादृच्छिक टेक्स्ट बनाएँ। विज़ुअल टेस्ट, क्रिएटिव प्लेसहोल्डर और सैंपल कंटेंट के लिए आदर्श।",
  "tags": [
    "यादृच्छिक पाठ",
    "इमोजी जनरेटर",
    "इमोजी के साथ पाठ",
    "मज़ेदार प्लेसहोल्डर",
    "इमोजी जनरेटर",
    "लोरेम इप्सुम इमोजी के साथ",
    "रचनात्मक पाठ उत्पन्न करें"
  ],
  "category": "जेनरेटर",
  "paragraphs": "पैराग्राफ",
  "style": "शैली",
  "casual": "अनौपचारिक",
  "tech": "तकनीक",
  "funny": "मजाक में कहा",
  "mix": "मिश्रित",
  "generate": "उत्पन्न करने के लिए",
  "placeholder": "परिणाम यहां दिखाई देगा"
}